connectivity_check/__init__.py
connectivity_check/__main__.py
connectivity_check/check_cert.py
connectivity_check/check_content.py
connectivity_check/check_latency.py
connectivity_check/check_routing.py
connectivity_check/check_speed_cloudflare.py
connectivity_check/check_speed_ookla.py
connectivity_check/checks.py
connectivity_check/datadog.py
connectivity_check/exceptions.py
connectivity_check-2023.10.2.dist-info/LICENSE
connectivity_check-2023.10.2.dist-info/METADATA
connectivity_check-2023.10.2.dist-info/WHEEL
connectivity_check-2023.10.2.dist-info/entry_points.txt
connectivity_check-2023.10.2.dist-info/RECORD
