Metadata-Version: 2.1
Name: connectivity-check
Version: 2023.10.2
Summary: Network and Website Connectivity Checks with DataDog metrics reporting
Author: Schlomo Schapiro
Author-email: schlomo+connectivity-check@schapiro.org
Requires-Python: >=3.10,<4.0
Classifier: Programming Language :: Python :: 3
Classifier: Programming Language :: Python :: 3.10
Classifier: Programming Language :: Python :: 3.11
Requires-Dist: bs4 (>=0.0.1,<0.0.2)
Requires-Dist: cloudflarepycli (>=1.8.1,<2.0.0)
Requires-Dist: cryptography (>=41.0.5,<42.0.0)
Requires-Dist: datadog (>=0.45.0,<0.46.0)
Requires-Dist: fire (>=0.5.0,<0.6.0)
Requires-Dist: pip-system-certs (>=4.0,<5.0)
Requires-Dist: pyroute2 (>=0.7.6,<0.8.0)
Requires-Dist: python-box (>=7.1.1,<8.0.0)
Requires-Dist: pyyaml (>=6.0.1,<7.0.0)
Requires-Dist: requests (>=2.31.0,<3.0.0)
Requires-Dist: requests-toolbelt (>=1.0.0,<2.0.0)
Requires-Dist: scapy (>=2.5.0,<3.0.0)
Requires-Dist: schema (>=0.7.5,<0.8.0)
Requires-Dist: speedtest-cli (>=2.1.3,<3.0.0)
Requires-Dist: tcp-latency (>=0.0.12,<0.0.13)
Requires-Dist: wres (>=1.0.3,<2.0.0)
